odoo/addons/base_time_window/README.rst
odoo/addons/base_time_window/__init__.py
odoo/addons/base_time_window/__manifest__.py
odoo/addons/base_time_window/data/time_weekday.xml
odoo/addons/base_time_window/i18n/base_time_window.pot
odoo/addons/base_time_window/i18n/es.po
odoo/addons/base_time_window/i18n/es_AR.po
odoo/addons/base_time_window/i18n/it.po
odoo/addons/base_time_window/models/__init__.py
odoo/addons/base_time_window/models/time_weekday.py
odoo/addons/base_time_window/models/time_window_mixin.py
odoo/addons/base_time_window/readme/CONTRIBUTORS.md
odoo/addons/base_time_window/readme/CREDITS.md
odoo/addons/base_time_window/readme/DESCRIPTION.md
odoo/addons/base_time_window/readme/ROADMAP.md
odoo/addons/base_time_window/readme/USAGE.md
odoo/addons/base_time_window/security/ir.model.access.xml
odoo/addons/base_time_window/static/description/icon.png
odoo/addons/base_time_window/static/description/index.html
odoo/addons/base_time_window/tests/__init__.py
odoo/addons/base_time_window/tests/test_models.py
odoo/addons/base_time_window/tests/test_time_weekday.py
odoo/addons/base_time_window/tests/test_time_window_mixin.py
odoo/addons/base_time_window/tests/test_weekday.py
odoo_addon_base_time_window-18.0.1.1.0.dist-info/METADATA
odoo_addon_base_time_window-18.0.1.1.0.dist-info/WHEEL
odoo_addon_base_time_window-18.0.1.1.0.dist-info/top_level.txt
odoo_addon_base_time_window-18.0.1.1.0.dist-info/RECORD
